ckernel/__init__.py
ckernel/__main__.py
ckernel/async_command.py
ckernel/autocompile_kernel.py
ckernel/base_kernel.py
ckernel/log.py
ckernel/main.py
ckernel/resource.py
ckernel/trigger.py
ckernel/util.py
ckernel/resources/__init__.py
ckernel/resources/ck_input_wrappers.c
ckernel/resources/kernel.sh
ckernel-0.5.3.dist-info/LICENSE
ckernel-0.5.3.dist-info/METADATA
ckernel-0.5.3.dist-info/WHEEL
ckernel-0.5.3.dist-info/entry_points.txt
ckernel-0.5.3.dist-info/top_level.txt
ckernel-0.5.3.dist-info/RECORD
