Metadata-Version: 2.1
Name: ckernel
Version: 0.5.3
Summary: Provides a Jupyter kernel which allows automatic compilation and execution of C/C++ code from a notebook environment.
Author: Adam Tuft
License: BSD-3-Clause
Project-URL: Homepage, https://c-kernel.readthedocs.io/en/latest/index.html
Project-URL: Bug Tracker, https://github.com/adamtuft/c-kernel/issues
Keywords: jupyter,notebook,kernel,c,c++
Classifier: Development Status :: 3 - Alpha
Classifier: Programming Language :: C
Classifier: Programming Language :: C++
Classifier: Topic :: Education
Classifier: Framework :: IPython
Classifier: Framework :: Jupyter
Classifier: Operating System :: POSIX :: Linux
Requires-Python: >=3.8
License-File: LICENSE
Requires-Dist: sysv-ipc
Requires-Dist: ipykernel
Requires-Dist: jupyter-client
Requires-Dist: colorama
Requires-Dist: notebook
